[{"name":"6780","area":"Lower Barreston","score":46,"vnum":"6780","names":["beautiful","mithril","fine","dagger"],"short":"a fine mithril dagger","long":"A beautiful mithril dagger has been misplaced.","material":["metal"],"submaterial":["mithril"],"itemType":"weapon","extraflags":[],"wearFlags":["takeable","wield"],"quality":59,"rarity":"not found randomly","oldowner":" ","values":["dagger","10","9","stab","D"],"valueFlags":["weapon class: (dagger)","damage : (10d9)","weapon type: (stab)","special type: (sharp)"],"furniture":{"maxPeople":"1","maxWeight":"0","healBonus":"0","manaBonus":"0","flags":["stand on"]},"level":"40","weight":"45","cost":"4532","totalAllowed":"unlimited","totalCurrent":"0","condition":"masterful","affects":[{"name":"hitroll","amount":"3"},{"name":"damroll","amount":"2"}]},{"name":"6838","area":"Lower Barreston","score":45,"vnum":"6838","names":["hook-ended","ended","sharp","dagger","wicked"],"short":"a hook-ended dagger","long":"This sharp dagger has a wicked hook on the end.","material":["metal"],"submaterial":["steel"],"itemType":"weapon","extraflags":[],"wearFlags":["takeable","wield"],"quality":43,"rarity":"not found randomly","oldowner":" ","values":["dagger","6","6","stab","H"],"valueFlags":["weapon class: (dagger)","damage : (6d6)","weapon type: (stab)","special type: (poison)"],"furniture":{"maxPeople":"1","maxWeight":"0","healBonus":"0","manaBonus":"0","flags":["stand on"]},"level":"18","weight":"50","cost":"5500","totalAllowed":"unlimited","totalCurrent":"0","condition":"masterful","affects":[{"name":"damroll","amount":"3"},{"name":"hitroll","amount":"1"}]},{"name":"6841","area":"Lower Barreston","score":42,"vnum":"6841","names":["very","sharp","steel","glass","cutter"],"short":"a glass cutter","long":"A very sharp steel glass cutter glints here.","material":["metal"],"submaterial":["steel"],"itemType":"jewelry","extraflags":[],"wearFlags":["takeable","hold"],"quality":45,"rarity":"not found randomly","oldowner":" ","values":["0","0","0","0","0"],"valueFlags":["unknown type"],"furniture":{"maxPeople":"1","maxWeight":"0","healBonus":"0","manaBonus":"0","flags":["stand on"]},"level":"24","weight":"15","cost":"3500","totalAllowed":"unlimited","totalCurrent":"0","condition":"masterful","affects":[{"name":"damroll","amount":"5"},{"name":"strength","amount":"1"}]},{"name":"6836","area":"Lower Barreston","score":35,"vnum":"6836","names":["jagged","steel","dagger"],"short":"a jagged steel dagger","long":"A jagged dagger has a brown stain along the edge.","material":["metal"],"submaterial":["steel"],"itemType":"weapon","extraflags":[],"wearFlags":["takeable","wield"],"quality":52,"rarity":"not found randomly","oldowner":" ","values":["dagger","5","5","stab","H"],"valueFlags":["weapon class: (dagger)","damage : (5d5)","weapon type: (stab)","special type: (poison)"],"furniture":{"maxPeople":"1","maxWeight":"0","healBonus":"0","manaBonus":"0","flags":["stand on"]},"level":"14","weight":"50","cost":"3500","totalAllowed":"unlimited","totalCurrent":"0","condition":"masterful","affects":[{"name":"hitroll","amount":"2"},{"name":"dexterity","amount":"1"}]},{"name":"6837","area":"Lower Barreston","score":34,"vnum":"6837","names":["slender","longsword","sword","brown-stained","stained","blade"],"short":"a slender longsword","long":"A longsword with a slender, brown-stained blade is here.","material":["metal"],"submaterial":["steel"],"itemType":"weapon","extraflags":[],"wearFlags":["takeable","wield"],"quality":49,"rarity":"not found randomly","oldowner":" ","values":["sword","5","6","slash","H"],"valueFlags":["weapon class: (sword)","damage : (5d6)","weapon type: (slash)","special type: (poison)"],"furniture":{"maxPeople":"1","maxWeight":"0","healBonus":"0","manaBonus":"0","flags":["stand on"]},"level":"16","weight":"120","cost":"4500","totalAllowed":"unlimited","totalCurrent":"0","condition":"masterful","affects":[{"name":"damroll","amount":"2"}]},{"name":"6772","area":"Lower Barreston","score":23,"vnum":"6772","names":["flame-colored","colored","bright","red","robe"],"short":"a {Rbright red{x robe","long":"A flame-colored robe has been piled here.","material":["clothing"],"submaterial":["cotton"],"itemType":"armor","extraflags":[],"wearFlags":["takeable","body"],"quality":49,"rarity":"not found randomly","oldowner":" ","values":["AB","B","B","A","0"],"valueFlags":["pierce: (3)","bash: (2)","slash: (2)","vs magic: (1)"],"furniture":{"maxPeople":"1","maxWeight":"0","healBonus":"0","manaBonus":"0","flags":["stand on"]},"level":"27","weight":"70","cost":"1097","totalAllowed":"unlimited","totalCurrent":"0","condition":"exceptional","affects":[{"name":"damroll","amount":"1"},{"name":"hitroll","amount":"4"}]},{"name":"6778","area":"Lower Barreston","score":22,"vnum":"6778","names":["very","narrow","slim","dagger","tiny","handle","sharp"],"short":"a slim, sharp dagger","long":"A very narrow dagger with a tiny handle rests here.","material":["metal"],"submaterial":["steel"],"itemType":"weapon","extraflags":[],"wearFlags":["takeable","wield"],"quality":41,"rarity":"not found randomly","oldowner":" ","values":["dagger","10","9","stab","0"],"valueFlags":["weapon class: (dagger)","damage : (10d9)","weapon type: (stab)","special type: ()"],"furniture":{"maxPeople":"1","maxWeight":"0","healBonus":"0","manaBonus":"0","flags":["stand on"]},"level":"40","weight":"20","cost":"1854","totalAllowed":"unlimited","totalCurrent":"0","condition":"exceptional","affects":[{"name":"damroll","amount":"2"},{"name":"hitroll","amount":"2"}]},{"name":"6839","area":"Lower Barreston","score":21,"vnum":"6839","names":["short","garrote","piece","thin","silk","rope","wooden","handles"],"short":"a short garrote","long":"A piece of thin silk rope with wooden handles rests here.","material":["clothing"],"submaterial":["fine","silk"],"itemType":"jewelry","extraflags":[],"wearFlags":["takeable","hold"],"quality":45,"rarity":"not found randomly","oldowner":" ","values":["0","0","0","0","0"],"valueFlags":["unknown type"],"furniture":{"maxPeople":"1","maxWeight":"0","healBonus":"0","manaBonus":"0","flags":["stand on"]},"level":"20","weight":"20","cost":"2700","totalAllowed":"unlimited","totalCurrent":"0","condition":"masterful","affects":[{"name":"damroll","amount":"3"}]},{"name":"6799","area":"Lower Barreston","score":20,"vnum":"6799","names":["sharp","steel","sabre"],"short":"a sharp steel sabre","long":"This steel sabre carries a fine edge.","material":["metal"],"submaterial":["steel"],"itemType":"weapon","extraflags":[],"wearFlags":["takeable","wield"],"quality":43,"rarity":"not found randomly","oldowner":" ","values":["sword","10","7","slash","D"],"valueFlags":["weapon class: (sword)","damage : (10d7)","weapon type: (slash)","special type: (sharp)"],"furniture":{"maxPeople":"1","maxWeight":"0","healBonus":"0","manaBonus":"0","flags":["stand on"]},"level":"34","weight":"100","cost":"3018","totalAllowed":"unlimited","totalCurrent":"0","condition":"exceptional"},{"name":"6712","area":"Lower Barreston","score":19,"vnum":"6712","names":["ragged","cotton","robe","pile","rags"],"short":"a ragged cotton robe","long":"A pile of cotton rags rest here.","material":["clothing"],"submaterial":["cotton"],"itemType":"armor","extraflags":[],"wearFlags":["takeable","body"],"quality":49,"rarity":"not found randomly","oldowner":" ","values":["AB","AB","AB","B","0"],"valueFlags":["pierce: (3)","bash: (3)","slash: (3)","vs magic: (2)"],"furniture":{"maxPeople":"1","maxWeight":"0","healBonus":"0","manaBonus":"0","flags":["stand on"]},"level":"28","weight":"120","cost":"1241","totalAllowed":"unlimited","totalCurrent":"0","condition":"outstanding","affects":[{"name":"hitroll","amount":"3"},{"name":"damroll","amount":"1"}]},{"name":"6840","area":"Lower Barreston","score":14,"vnum":"6840","names":["bunch","leather","straps","dagger","spring-sheath","sheath"],"short":"a dagger spring-sheath","long":"A bunch of leather straps have been dropped here.","material":["clothing"],"submaterial":["soft","leather"],"itemType":"jewelry","extraflags":[],"wearFlags":["takeable","hold"],"quality":47,"rarity":"not found randomly","oldowner":" ","values":["0","0","0","0","0"],"valueFlags":["unknown type"],"furniture":{"maxPeople":"1","maxWeight":"0","healBonus":"0","manaBonus":"0","flags":["stand on"]},"level":"22","weight":"40","cost":"3000","totalAllowed":"unlimited","totalCurrent":"0","condition":"masterful","affects":[{"name":"dexterity","amount":"2"}]},{"name":"6773","area":"Lower Barreston","score":14,"vnum":"6773","names":["bright","red","cap"],"short":"a {Rbright red{x cap","long":"A bright red cap rests upon the ground here.","material":["clothing"],"submaterial":[""],"itemType":"trash","extraflags":[],"wearFlags":["takeable","head"],"quality":41,"rarity":"not found randomly","oldowner":" ","values":["0","0","0","0","0"],"valueFlags":["unknown type"],"furniture":{"maxPeople":"1","maxWeight":"0","healBonus":"0","manaBonus":"0","flags":["stand on"]},"level":"27","weight":"20","cost":"783","totalAllowed":"unlimited","totalCurrent":"0","condition":"exceptional","affects":[{"name":"wisdom","amount":"1"},{"name":"intelligence","amount":"1"}]},{"name":"6713","area":"Lower Barreston","score":12,"vnum":"6713","names":["twin","piles","bound","rags","shoes"],"short":"bound rags","long":"Twin piles of rags seem to be bound into something resembling shoes.","material":["clothing"],"submaterial":["cotton"],"itemType":"armor","extraflags":[],"wearFlags":["takeable","feet"],"quality":43,"rarity":"not found randomly","oldowner":" ","values":["AB","AB","AB","B","0"],"valueFlags":["pierce: (3)","bash: (3)","slash: (3)","vs magic: (2)"],"furniture":{"maxPeople":"1","maxWeight":"0","healBonus":"0","manaBonus":"0","flags":["stand on"]},"level":"28","weight":"50","cost":"1029","totalAllowed":"unlimited","totalCurrent":"0","condition":"outstanding","affects":[{"name":"ac","amount":"-4"}]},{"name":"6781","area":"Lower Barreston","score":11,"vnum":"6781","names":["dented","steel","shield"],"short":"a dented steel shield","long":"The steel shield here has a large dent in the top.","material":["metal"],"submaterial":["steel"],"itemType":"armor","extraflags":[],"wearFlags":["takeable","shield"],"quality":40,"rarity":"not found randomly","oldowner":" ","values":["AB","C","C","B","0"],"valueFlags":["pierce: (3)","bash: (4)","slash: (4)","vs magic: (2)"],"furniture":{"maxPeople":"1","maxWeight":"0","healBonus":"0","manaBonus":"0","flags":["stand on"]},"level":"40","weight":"180","cost":"90","totalAllowed":"unlimited","totalCurrent":"0","condition":"outstanding","affects":[{"name":"strength","amount":"1"},{"name":"hitroll","amount":"1"}]},{"name":"6774","area":"Lower Barreston","score":11,"vnum":"6774","names":["carved","wooden","flame","symbol","Vyrul"],"short":"a wooden symbol of {RVyrul{x","long":"A carved wooden flame rests here.","material":["wood"],"submaterial":["hardwood"],"itemType":"armor","extraflags":[],"wearFlags":["takeable","neck"],"quality":58,"rarity":"not found randomly","oldowner":" ","values":["C","AB","B","B","0"],"valueFlags":["pierce: (4)","bash: (3)","slash: (2)","vs magic: (2)"],"furniture":{"maxPeople":"1","maxWeight":"0","healBonus":"0","manaBonus":"0","flags":["stand on"]},"level":"29","weight":"20","cost":"1564","totalAllowed":"unlimited","totalCurrent":"0","condition":"exceptional","affects":[{"name":"ac","amount":"-2"},{"name":"saves","amount":"-1"}]},{"name":"6843","area":"Lower Barreston","score":8,"vnum":"6843","names":["lightly","patched","fairly","new","wool","smock"],"short":"a fairly new wool smock","long":"A lightly patched smock has been dropped here.","material":["clothing"],"submaterial":["wool"],"itemType":"armor","extraflags":[],"wearFlags":["takeable","body"],"quality":47,"rarity":"not found randomly","oldowner":" ","values":["B","B","A","B","0"],"valueFlags":["pierce: (2)","bash: (2)","slash: (1)","vs magic: (2)"],"furniture":{"maxPeople":"1","maxWeight":"0","healBonus":"0","manaBonus":"0","flags":["stand on"]},"level":"36","weight":"90","cost":"125","totalAllowed":"unlimited","totalCurrent":"0","condition":"masterful","affects":[{"name":"hitroll","amount":"2"}]},{"name":"6776","area":"Lower Barreston","score":4,"vnum":"6776","names":["grime-coated","coated","cotton","tunic","dirty"],"short":"a dirty cotton tunic","long":"A grime-coated cotton tunic makes the air smell.","material":["clothing"],"submaterial":["cotton"],"itemType":"armor","extraflags":[],"wearFlags":["takeable","body"],"quality":57,"rarity":"not found randomly","oldowner":" ","values":["A","A","A","0","0"],"valueFlags":["pierce: (1)","bash: (1)","slash: (1)","vs magic: (0)"],"furniture":{"maxPeople":"1","maxWeight":"0","healBonus":"0","manaBonus":"0","flags":["stand on"]},"level":"20","weight":"65","cost":"10","totalAllowed":"unlimited","totalCurrent":"0","condition":"outstanding","affects":[{"name":"hitroll","amount":"1"}]}]