[{"name":"26045","area":"Uchduruk","score":264013,"vnum":"26045","names":["moongleam","gleam","sylune"],"short":"{WMoon{CGleam{x","long":"{WMoonlight {Cgleams {Wunnaturally here, bent into the shape of a bow.{x","material":["miscellaneous"],"submaterial":["light"],"itemType":"weapon","extraflags":["glow","hum","magic","nonmetal","burnproof","noid"],"wearFlags":["takeable","wield"],"quality":60,"rarity":"not found randomly","oldowner":" ","values":["exotic","100","100","pierce","ABDFGHIJ"],"valueFlags":["weapon class: (exotic)","damage : (100d100)","weapon type: (pierce)","special type: (flaming,frost,sharp,two-handed,shocking,poison,razor,imbued)"],"furniture":{"maxPeople":"1","maxWeight":"0","healBonus":"0","manaBonus":"0","flags":["stand on"]},"level":"0","weight":"0","cost":"0","totalAllowed":"unlimited","totalCurrent":"2","condition":"masterful","affects":[{"name":"hitroll","amount":"23994"},{"name":"damroll","amount":"23991"}]},{"name":"26000","area":"Uchduruk","score":10528,"vnum":"26000","names":["can","whoop","ass"],"short":"a can of {YWhoop-Ass{D(tm){x","long":"A can of {YWhoop-Ass{D(tm){x sits on the ground.","material":["miscellaneous"],"submaterial":["spirit"],"itemType":"armor","extraflags":["glow","hum","magic","bless"],"wearFlags":["takeable","hold"],"quality":58,"rarity":"not found randomly","oldowner":" ","values":["CHIJ","CHIJ","CHIJ","CHIJ","0"],"valueFlags":["pierce: (900)","bash: (900)","slash: (900)","vs magic: (900)"],"furniture":{"maxPeople":"1","maxWeight":"999","healBonus":"999","manaBonus":"999","flags":["stand on","sit on","rest on","sleep in"]},"level":"0","weight":"0","cost":"1","totalAllowed":"unlimited","totalCurrent":"3","condition":"masterful","affects":[{"name":"none","amount":"0"},{"name":"damroll","amount":"956"},{"name":"hitroll","amount":"959"}]},{"name":"26014","area":"Uchduruk","score":130,"vnum":"26014","names":["stout","short","sword","shortsword"],"short":"a stout shortsword","long":"A stout shortsword hums malevolently.","material":["metal"],"submaterial":["adamantite"],"itemType":"weapon","extraflags":["hum","evil","nodrop","antigood","antineutral","noremove"],"wearFlags":["takeable","wield"],"quality":41,"rarity":"not found randomly","oldowner":" ","values":["sword","9","13","bite","D"],"valueFlags":["weapon class: (sword)","damage : (9d13)","weapon type: (bite)","special type: (sharp)"],"furniture":{"maxPeople":"1","maxWeight":"0","healBonus":"0","manaBonus":"0","flags":["stand on"]},"level":"60","weight":"271","cost":"4300","totalAllowed":"unlimited","totalCurrent":"3","condition":"masterful","affects":[{"name":"ac","amount":"-20"},{"name":"strength","amount":"1"},{"name":"constitution","amount":"1"},{"name":"hitroll","amount":"2"},{"name":"damroll","amount":"4"}]},{"name":"26033","area":"Uchduruk","score":105,"vnum":"26033","names":["helm","uruk"],"short":"an orcish Uruk's helm","long":"A helm of orcish design has been abandoned here.","material":["metal"],"submaterial":["cold","steel"],"itemType":"armor","extraflags":["dark","evil","antigood","antineutral","noremove","rotdeath","nouncurse","noid"],"wearFlags":["takeable","head"],"quality":52,"rarity":"not found randomly","oldowner":" ","values":["AD","AD","AD","AC","0"],"valueFlags":["pierce: (9)","bash: (9)","slash: (9)","vs magic: (5)"],"furniture":{"maxPeople":"1","maxWeight":"0","healBonus":"0","manaBonus":"0","flags":["stand on"]},"level":"45","weight":"200","cost":"7623","totalAllowed":"unlimited","totalCurrent":"1","condition":"masterful","affects":[{"name":"health","amount":"100"},{"name":"hitroll","amount":"-4"},{"name":"wisdom","amount":"1"},{"name":"intelligence","amount":"2"}]},{"name":"26015","area":"Uchduruk","score":99,"vnum":"26015","names":["aura","leadership"],"short":"an {CAura{x of{Y Leadership{x","long":"{xA powerful aura hovers in the air.","material":["mineral"],"submaterial":["onyx"],"itemType":"armor","extraflags":["hum","antineutral"],"wearFlags":["takeable","float"],"quality":53,"rarity":"not found randomly","oldowner":" ","values":["CD","CD","CD","BC","0"],"valueFlags":["pierce: (12)","bash: (12)","slash: (12)","vs magic: (6)"],"furniture":{"maxPeople":"1","maxWeight":"0","healBonus":"0","manaBonus":"0","flags":["stand on"]},"level":"60","weight":"60","cost":"5400","totalAllowed":"unlimited","totalCurrent":"3","condition":"masterful","affects":[{"name":"damroll","amount":"4"},{"name":"hitroll","amount":"4"},{"name":"health","amount":"55"}]},{"name":"26022","area":"Uchduruk","score":89,"vnum":"26022","names":["legbone","bone","scorpion"],"short":"{xa legbone of a {rhuge{D stone troll{x","long":"A huge, petrified legbone lies on the ground.","material":["creature"],"submaterial":["bone"],"itemType":"weapon","extraflags":["dark","evil"],"wearFlags":["takeable","wield"],"quality":55,"rarity":"not found randomly","oldowner":" ","values":["mace","10","12","pound","E"],"valueFlags":["weapon class: (mace)","damage : (10d12)","weapon type: (pound)","special type: (vorpal)"],"furniture":{"maxPeople":"1","maxWeight":"0","healBonus":"0","manaBonus":"0","flags":["stand on"]},"level":"60","weight":"80","cost":"3200","totalAllowed":"unlimited","totalCurrent":"4","condition":"masterful","affects":[{"name":"hitroll","amount":"5"},{"name":"damroll","amount":"7"}]},{"name":"26021","area":"Uchduruk","score":75,"vnum":"26021","names":["the","stinger"],"short":"{DT{wh{De {DS{wt{Di{wn{Dg{we{Dr{x","long":"An insect stinger the size of a shortsword is dripping with poison.","material":["creature"],"submaterial":["fang"],"itemType":"weapon","extraflags":["glow"],"wearFlags":["takeable","wield"],"quality":57,"rarity":"not found randomly","oldowner":" ","values":["dagger","9","12","sting","H"],"valueFlags":["weapon class: (dagger)","damage : (9d12)","weapon type: (sting)","special type: (poison)"],"furniture":{"maxPeople":"1","maxWeight":"0","healBonus":"0","manaBonus":"0","flags":["stand on"]},"level":"60","weight":"100","cost":"212","totalAllowed":"unlimited","totalCurrent":"1","condition":"masterful","affects":[{"name":"hitroll","amount":"5"},{"name":"damroll","amount":"5"}]},{"name":"26017","area":"Uchduruk","score":65,"vnum":"26017","names":["flail","obedience"],"short":"the {DFlail{x of {yObedience{x","long":"A cruel looking flail lies on the ground.","material":["metal"],"submaterial":["steel"],"itemType":"weapon","extraflags":[],"wearFlags":["takeable","wield"],"quality":43,"rarity":"not found randomly","oldowner":" ","values":["flail","12","8","wrath","G"],"valueFlags":["weapon class: (flail)","damage : (12d8)","weapon type: (wrath)","special type: (shocking)"],"furniture":{"maxPeople":"1","maxWeight":"0","healBonus":"0","manaBonus":"0","flags":["stand on"]},"level":"50","weight":"100","cost":"4500","totalAllowed":"unlimited","totalCurrent":"1","condition":"masterful","affects":[{"name":"hitroll","amount":"4"},{"name":"damroll","amount":"7"}]},{"name":"26016","area":"Uchduruk","score":62,"vnum":"26016","names":["glowing","black","rock"],"short":"a {Yglowing {Dblack{x rock","long":"A fist sized rock sits here on the ground, {Yglowing{x.","material":["mineral"],"submaterial":["onyx"],"itemType":"light","extraflags":["glow","hum","rotdeath","meltdrop"],"wearFlags":["takeable","hold"],"quality":47,"rarity":"not found randomly","oldowner":" ","values":["0","0","ABCDEFGHIJKLMNOPQRSTUVWXYZabcdef","0","0"],"valueFlags":["light value: (67108926)"],"furniture":{"maxPeople":"1","maxWeight":"0","healBonus":"0","manaBonus":"0","flags":["stand on"]},"level":"60","weight":"300","cost":"4300","totalAllowed":"unlimited","totalCurrent":"1","condition":"masterful","affects":[{"name":"dexterity","amount":"1"},{"name":"hitroll","amount":"5"},{"name":"damroll","amount":"5"}]},{"name":"26007","area":"Uchduruk","score":61,"vnum":"26007","names":["stone","troll","rock","brain"],"short":"a little brain made of rock","long":"An odd looking rock sits on the ground.  It looks like a small brain.","material":["mineral"],"submaterial":["stone"],"itemType":"trash","extraflags":["hum","evil","hidden"],"wearFlags":["takeable","float"],"quality":56,"rarity":"not found randomly","oldowner":" ","values":["0","0","0","0","0"],"valueFlags":["unknown type"],"furniture":{"maxPeople":"1","maxWeight":"0","healBonus":"0","manaBonus":"0","flags":["stand on"]},"level":"54","weight":"20","cost":"10100","totalAllowed":"unlimited","totalCurrent":"2","condition":"masterful","affects":[{"name":"hitroll","amount":"6"},{"name":"intelligence","amount":"1"},{"name":"mana","amount":"30"}]},{"name":"26002","area":"Uchduruk","score":44,"vnum":"26002","names":["elven","brigandine"],"short":"{gElven {yBrigandine{x","long":"A suit of brigandine armor has been discarded here.","material":["clothing"],"submaterial":["leather"],"itemType":"armor","extraflags":["magic","antievil"],"wearFlags":["takeable","body"],"quality":60,"rarity":"not found randomly","oldowner":" ","values":["D","D","D","AC","0"],"valueFlags":["pierce: (8)","bash: (8)","slash: (8)","vs magic: (5)"],"furniture":{"maxPeople":"1","maxWeight":"0","healBonus":"0","manaBonus":"0","flags":[]},"level":"40","weight":"70","cost":"3313","totalAllowed":"unlimited","totalCurrent":"4","condition":"masterful","affects":[{"name":"hitroll","amount":"4"},{"name":"damroll","amount":"4"}]},{"name":"26032","area":"Uchduruk","score":42,"vnum":"26032","names":["iron","boots"],"short":"iron-shod boots","long":"Leather boots, plated with iron, stand in the corner.","material":["metal"],"submaterial":["iron"],"itemType":"armor","extraflags":["dark","evil","antigood","antineutral"],"wearFlags":["takeable","feet"],"quality":41,"rarity":"not found randomly","oldowner":" ","values":["AD","AD","AD","AC","0"],"valueFlags":["pierce: (9)","bash: (9)","slash: (9)","vs magic: (5)"],"furniture":{"maxPeople":"1","maxWeight":"0","healBonus":"0","manaBonus":"0","flags":["stand on"]},"level":"45","weight":"250","cost":"5801","totalAllowed":"unlimited","totalCurrent":"1","condition":"masterful","affects":[{"name":"strength","amount":"1"},{"name":"constitution","amount":"1"},{"name":"damroll","amount":"4"},{"name":"move","amount":"-50"}]},{"name":"26027","area":"Uchduruk","score":42,"vnum":"26027","names":["heavy","steel","broadsword"],"short":"a heavy steel broadsword","long":"A steel broadsword rests on the ground.  It looks heavy.","material":["metal"],"submaterial":["steel"],"itemType":"weapon","extraflags":["glow"],"wearFlags":["takeable","wield"],"quality":53,"rarity":"not found randomly","oldowner":" ","values":["sword","6","13","slash","D"],"valueFlags":["weapon class: (sword)","damage : (6d13)","weapon type: (slash)","special type: (sharp)"],"furniture":{"maxPeople":"1","maxWeight":"0","healBonus":"0","manaBonus":"0","flags":["stand on"]},"level":"40","weight":"400","cost":"20000","totalAllowed":"unlimited","totalCurrent":"6","condition":"masterful","affects":[{"name":"hitroll","amount":"2"},{"name":"damroll","amount":"2"}]},{"name":"26026","area":"Uchduruk","score":42,"vnum":"26026","names":["curved","dagger"],"short":"a curved dagger","long":"A dagger with a wickedly curved blade lies in the dirt.","material":["metal"],"submaterial":["steel"],"itemType":"weapon","extraflags":["glow"],"wearFlags":["takeable","wield"],"quality":60,"rarity":"not found randomly","oldowner":" ","values":["dagger","6","14","pierce","H"],"valueFlags":["weapon class: (dagger)","damage : (6d14)","weapon type: (pierce)","special type: (poison)"],"furniture":{"maxPeople":"1","maxWeight":"0","healBonus":"0","manaBonus":"0","flags":["stand on"]},"level":"40","weight":"150","cost":"20000","totalAllowed":"unlimited","totalCurrent":"1","condition":"masterful","affects":[{"name":"hitroll","amount":"2"},{"name":"damroll","amount":"2"}]},{"name":"26025","area":"Uchduruk","score":42,"vnum":"26025","names":["broad","axe"],"short":"a broad-bladed axe","long":"A broad-bladed axe stands propped in one corner.","material":["metal"],"submaterial":["steel"],"itemType":"weapon","extraflags":["glow"],"wearFlags":["takeable","wield"],"quality":57,"rarity":"not found randomly","oldowner":" ","values":["axe","7","12","chop","D"],"valueFlags":["weapon class: (axe)","damage : (7d12)","weapon type: (chop)","special type: (sharp)"],"furniture":{"maxPeople":"1","maxWeight":"0","healBonus":"0","manaBonus":"0","flags":["stand on"]},"level":"40","weight":"300","cost":"20000","totalAllowed":"unlimited","totalCurrent":"1","condition":"masterful","affects":[{"name":"hitroll","amount":"2"},{"name":"damroll","amount":"2"}]},{"name":"26020","area":"Uchduruk","score":40,"vnum":"26020","names":["orcish","nosepicker","dagger"],"short":"an {gOrcish {ynosepicker{x","long":"A long, slender dagger of elvish make, it was far too dainty for the previous owner to use as a weapon.","material":["wood"],"submaterial":["softwood"],"itemType":"weapon","extraflags":["dark"],"wearFlags":["takeable","wield"],"quality":58,"rarity":"not found randomly","oldowner":" ","values":["dagger","6","12","slime","H"],"valueFlags":["weapon class: (dagger)","damage : (6d12)","weapon type: (slime)","special type: (poison)"],"furniture":{"maxPeople":"1","maxWeight":"0","healBonus":"0","manaBonus":"0","flags":["stand on"]},"level":"35","weight":"10","cost":"212","totalAllowed":"unlimited","totalCurrent":"2","condition":"masterful","affects":[{"name":"hitroll","amount":"5"}]},{"name":"26011","area":"Uchduruk","score":40,"vnum":"26011","names":["heavy","mace","diplomacy"],"short":"{xa mace nicknamed {DDiplomacy{x","long":"A heavy and brutal looking mace lies in the dirt.","material":["metal"],"submaterial":["adamantite"],"itemType":"weapon","extraflags":["dark","evil"],"wearFlags":["takeable","wield"],"quality":42,"rarity":"not found randomly","oldowner":" ","values":["mace","10","9","crush","0"],"valueFlags":["weapon class: (mace)","damage : (10d9)","weapon type: (crush)","special type: ()"],"furniture":{"maxPeople":"1","maxWeight":"0","healBonus":"0","manaBonus":"0","flags":["stand on"]},"level":"45","weight":"100","cost":"1750","totalAllowed":"unlimited","totalCurrent":"4","condition":"masterful","affects":[{"name":"hitroll","amount":"3"},{"name":"damroll","amount":"3"},{"name":"strength","amount":"1"}]},{"name":"26003","area":"Uchduruk","score":40,"vnum":"26003","names":["mithril","longsword"],"short":"{Da {WM{wi{Wt{wh{Wr{wi{Wl{D Longsword{x","long":"A longsword rests on the ground, gleaming brightly.","material":["metal"],"submaterial":["mithril"],"itemType":"weapon","extraflags":["hum","antievil"],"wearFlags":["takeable","wield"],"quality":53,"rarity":"not found randomly","oldowner":" ","values":["sword","8","9","slash","0"],"valueFlags":["weapon class: (sword)","damage : (8d9)","weapon type: (slash)","special type: ()"],"furniture":{"maxPeople":"1","maxWeight":"0","healBonus":"0","manaBonus":"0","flags":["stand on"]},"level":"40","weight":"120","cost":"15200","totalAllowed":"unlimited","totalCurrent":"1","condition":"masterful","affects":[{"name":"damroll","amount":"4"},{"name":"hitroll","amount":"3"}]},{"name":"26013","area":"Uchduruk","score":38,"vnum":"26013","names":["heavy","glaive"],"short":"a heavy glaive","long":"A sturdy glaive is collecting dust.","material":["metal"],"submaterial":["steel"],"itemType":"weapon","extraflags":["hum"],"wearFlags":["takeable","wield"],"quality":41,"rarity":"not found randomly","oldowner":" ","values":["polearm","5","18","cleave","F"],"valueFlags":["weapon class: (polearm)","damage : (5d18)","weapon type: (cleave)","special type: (two-handed)"],"furniture":{"maxPeople":"1","maxWeight":"0","healBonus":"0","manaBonus":"0","flags":["stand on"]},"level":"45","weight":"230","cost":"3210","totalAllowed":"unlimited","totalCurrent":"10","condition":"masterful","affects":[{"name":"hitroll","amount":"6"},{"name":"damroll","amount":"2"}]},{"name":"26005","area":"Uchduruk","score":35,"vnum":"26005","names":["bracer","stone","troll","hide"],"short":"a {Dtroll{x hide bracer","long":"A bracer made of {Dstone{x lies on the ground, humming.","material":["creature"],"submaterial":["hide"],"itemType":"armor","extraflags":["hum","noid"],"wearFlags":["takeable","wrist"],"quality":58,"rarity":"not found randomly","oldowner":" ","values":["A","AD","AD","A","0"],"valueFlags":["pierce: (1)","bash: (9)","slash: (9)","vs magic: (1)"],"furniture":{"maxPeople":"1","maxWeight":"0","healBonus":"0","manaBonus":"0","flags":["stand on"]},"level":"37","weight":"40","cost":"5455","totalAllowed":"unlimited","totalCurrent":"9","condition":"masterful","affects":[{"name":"damroll","amount":"5"}]},{"name":"26010","area":"Uchduruk","score":34,"vnum":"26010","names":["orcish","sergeant","rank","insignia","skin","pile"],"short":"{DThe {yRank {Dof {gSergeant{x","long":"Someone's been skinning orcs again, and they left a pile of it here.","material":["creature"],"submaterial":["hide"],"itemType":"armor","extraflags":["nonmetal"],"wearFlags":["takeable","arms"],"quality":41,"rarity":"not found randomly","oldowner":" ","values":["AD","AD","AD","AC","0"],"valueFlags":["pierce: (9)","bash: (9)","slash: (9)","vs magic: (5)"],"furniture":{"maxPeople":"1","maxWeight":"0","healBonus":"0","manaBonus":"0","flags":["stand on"]},"level":"45","weight":"250","cost":"5801","totalAllowed":"unlimited","totalCurrent":"2","condition":"masterful","affects":[{"name":"dexterity","amount":"1"},{"name":"strength","amount":"1"},{"name":"saves","amount":"-4"}]},{"name":"26012","area":"Uchduruk","score":30,"vnum":"26012","names":["short","spear"],"short":"a short spear","long":"A short spear has been dropped here.","material":["metal"],"submaterial":["adamantite"],"itemType":"weapon","extraflags":["dark","evil"],"wearFlags":["takeable","wield"],"quality":47,"rarity":"not found randomly","oldowner":" ","values":["spear","8","11","stab","0"],"valueFlags":["weapon class: (spear)","damage : (8d11)","weapon type: (stab)","special type: ()"],"furniture":{"maxPeople":"1","maxWeight":"0","healBonus":"0","manaBonus":"0","flags":["stand on"]},"level":"45","weight":"50","cost":"1900","totalAllowed":"unlimited","totalCurrent":"11","condition":"masterful","affects":[{"name":"damroll","amount":"2"},{"name":"hitroll","amount":"4"}]},{"name":"26009","area":"Uchduruk","score":30,"vnum":"26009","names":["iron-bound","iron","bound","shield"],"short":"an {DIron-Bound {yShield{x","long":"An orcish made shield lies here, battered and well-used.","material":["metal"],"submaterial":["iron"],"itemType":"armor","extraflags":["bless"],"wearFlags":["takeable","shield"],"quality":58,"rarity":"not found randomly","oldowner":" ","values":["AD","AD","AD","AC","0"],"valueFlags":["pierce: (9)","bash: (9)","slash: (9)","vs magic: (5)"],"furniture":{"maxPeople":"1","maxWeight":"0","healBonus":"0","manaBonus":"0","flags":["stand on"]},"level":"45","weight":"90","cost":"6100","totalAllowed":"unlimited","totalCurrent":"3","condition":"masterful","affects":[{"name":"ac","amount":"-10"}]},{"name":"26008","area":"Uchduruk","score":27,"vnum":"26008","names":["stone","troll","skull"],"short":"the {Wskull{x of a {Dstone troll{x","long":"A skull made of stone sits here.","material":["creature"],"submaterial":["bone"],"itemType":"armor","extraflags":[],"wearFlags":["takeable","head"],"quality":45,"rarity":"not found randomly","oldowner":" ","values":["CD","CD","CD","BC","0"],"valueFlags":["pierce: (12)","bash: (12)","slash: (12)","vs magic: (6)"],"furniture":{"maxPeople":"1","maxWeight":"0","healBonus":"0","manaBonus":"0","flags":["stand on"]},"level":"59","weight":"100","cost":"80","totalAllowed":"unlimited","totalCurrent":"4","condition":"masterful","affects":[{"name":"damroll","amount":"5"},{"name":"hitroll","amount":"5"},{"name":"intelligence","amount":"-2"},{"name":"wisdom","amount":"-2"}]},{"name":"26030","area":"Uchduruk","score":22,"vnum":"26030","names":["three","headed","flail"],"short":"a three-headed flail","long":"A flail lies forgotten here, its three steel heads promising considerable damage to anything in their path.","material":["metal"],"submaterial":["steel"],"itemType":"weapon","extraflags":["glow"],"wearFlags":["takeable","wield"],"quality":59,"rarity":"not found randomly","oldowner":" ","values":["flail","6","13","beating","0"],"valueFlags":["weapon class: (flail)","damage : (6d13)","weapon type: (beating)","special type: ()"],"furniture":{"maxPeople":"1","maxWeight":"0","healBonus":"0","manaBonus":"0","flags":["stand on"]},"level":"40","weight":"250","cost":"20000","totalAllowed":"unlimited","totalCurrent":"1","condition":"masterful","affects":[{"name":"hitroll","amount":"2"},{"name":"damroll","amount":"2"}]},{"name":"26029","area":"Uchduruk","score":22,"vnum":"26029","names":["weighted","steel","chain"],"short":"a weighted chain","long":"A length of steel chain lies in a pile here, with heavy weights at either end.","material":["metal"],"submaterial":["steel"],"itemType":"weapon","extraflags":["glow"],"wearFlags":["takeable","wield"],"quality":52,"rarity":"not found randomly","oldowner":" ","values":["whip","8","10","grep","G"],"valueFlags":["weapon class: (whip)","damage : (8d10)","weapon type: (grep)","special type: (shocking)"],"furniture":{"maxPeople":"1","maxWeight":"0","healBonus":"0","manaBonus":"0","flags":["stand on"]},"level":"40","weight":"150","cost":"20000","totalAllowed":"unlimited","totalCurrent":"1","condition":"masterful","affects":[{"name":"hitroll","amount":"2"},{"name":"damroll","amount":"2"}]},{"name":"26028","area":"Uchduruk","score":22,"vnum":"26028","names":["flanged","mace"],"short":"a flanged steel mace","long":"A brutal-looking flanged mace has been discarded here.","material":["metal"],"submaterial":["steel"],"itemType":"weapon","extraflags":["glow"],"wearFlags":["takeable","wield"],"quality":55,"rarity":"not found randomly","oldowner":" ","values":["mace","10","8","crush","0"],"valueFlags":["weapon class: (mace)","damage : (10d8)","weapon type: (crush)","special type: ()"],"furniture":{"maxPeople":"1","maxWeight":"0","healBonus":"0","manaBonus":"0","flags":["stand on"]},"level":"40","weight":"250","cost":"20000","totalAllowed":"unlimited","totalCurrent":"1","condition":"masterful","affects":[{"name":"hitroll","amount":"2"},{"name":"damroll","amount":"2"}]},{"name":"26006","area":"Uchduruk","score":22,"vnum":"26006","names":["axe","notched"],"short":"a notched axe","long":"An axe lies here, the blade notched from misuse.","material":["metal"],"submaterial":["steel"],"itemType":"weapon","extraflags":["hum"],"wearFlags":["takeable","wield"],"quality":56,"rarity":"not found randomly","oldowner":" ","values":["axe","9","7","thwack","0"],"valueFlags":["weapon class: (axe)","damage : (9d7)","weapon type: (thwack)","special type: ()"],"furniture":{"maxPeople":"1","maxWeight":"0","healBonus":"0","manaBonus":"0","flags":["stand on"]},"level":"35","weight":"90","cost":"1911","totalAllowed":"unlimited","totalCurrent":"1","condition":"masterful","affects":[{"name":"hitroll","amount":"2"},{"name":"damroll","amount":"2"}]},{"name":"26031","area":"Uchduruk","score":21,"vnum":"26031","names":["iron","greaves"],"short":"iron greaves","long":"A set of simple iron greaves lie here on the ground.","material":["metal"],"submaterial":["iron"],"itemType":"armor","extraflags":[],"wearFlags":["takeable","legs"],"quality":42,"rarity":"not found randomly","oldowner":" ","values":["AD","AD","AD","AC","0"],"valueFlags":["pierce: (9)","bash: (9)","slash: (9)","vs magic: (5)"],"furniture":{"maxPeople":"1","maxWeight":"0","healBonus":"0","manaBonus":"0","flags":["stand on"]},"level":"45","weight":"400","cost":"4321","totalAllowed":"unlimited","totalCurrent":"1","condition":"masterful","affects":[{"name":"constitution","amount":"1"},{"name":"strength","amount":"2"}]},{"name":"26004","area":"Uchduruk","score":12,"vnum":"26004","names":["elven","boots","leather"],"short":"{gElven {yBoots{x","long":"Someone lost their {yboots{x.","material":["clothing"],"submaterial":["leather"],"itemType":"armor","extraflags":[],"wearFlags":["takeable","feet"],"quality":56,"rarity":"not found randomly","oldowner":" ","values":["BC","BC","BC","C","0"],"valueFlags":["pierce: (6)","bash: (6)","slash: (6)","vs magic: (4)"],"furniture":{"maxPeople":"1","maxWeight":"0","healBonus":"0","manaBonus":"0","flags":["stand on"]},"level":"40","weight":"70","cost":"2030","totalAllowed":"unlimited","totalCurrent":"1","condition":"masterful","affects":[{"name":"move","amount":"150"},{"name":"hitroll","amount":"3"}]},{"name":"26035","area":"Uchduruk","score":7,"vnum":"26035","names":["shield","uruk"],"short":"an orcish Uruk's shield","long":"A shield of orcish design lies here, discarded.","material":["metal"],"submaterial":["cold","steel"],"itemType":"armor","extraflags":["dark","evil","antigood","antineutral","noremove","noid"],"wearFlags":["takeable","shield"],"quality":58,"rarity":"not found randomly","oldowner":" ","values":["AD","AD","AD","AC","0"],"valueFlags":["pierce: (9)","bash: (9)","slash: (9)","vs magic: (5)"],"furniture":{"maxPeople":"1","maxWeight":"0","healBonus":"50","manaBonus":"0","flags":["stand on"]},"level":"45","weight":"300","cost":"6540","totalAllowed":"unlimited","totalCurrent":"1","condition":"masterful","affects":[{"name":"dexterity","amount":"-1"},{"name":"intelligence","amount":"-1"},{"name":"constitution","amount":"1"},{"name":"strength","amount":"2"}]},{"name":"26034","area":"Uchduruk","score":6,"vnum":"26034","names":["brigandine","leather","tunic"],"short":"brigandine","long":"A leather tunic lies in a heap, showing metal plates hidden on the inside.","material":["metal"],"submaterial":["cold","steel"],"itemType":"armor","extraflags":["dark","evil","antigood","antineutral"],"wearFlags":["takeable","body"],"quality":51,"rarity":"not found randomly","oldowner":" ","values":["AD","AD","AD","AC","0"],"valueFlags":["pierce: (9)","bash: (9)","slash: (9)","vs magic: (5)"],"furniture":{"maxPeople":"1","maxWeight":"0","healBonus":"0","manaBonus":"0","flags":["stand on"]},"level":"40","weight":"200","cost":"7623","totalAllowed":"unlimited","totalCurrent":"1","condition":"masterful","affects":[{"name":"hitroll","amount":"3"},{"name":"ac","amount":"2"}]}]